lactolyse/__about__.py
lactolyse/__init__.py
lactolyse/admin.py
lactolyse/apps.py
lactolyse/consumers.py
lactolyse/forms.py
lactolyse/models.py
lactolyse/protocol.py
lactolyse/registry.py
lactolyse/tests.py
lactolyse/urls.py
lactolyse/utils.py
lactolyse/analyses/__init__.py
lactolyse/analyses/base.py
lactolyse/analyses/conconi_test.py
lactolyse/analyses/critical_power.py
lactolyse/analyses/lactate_threshold.py
lactolyse/analyses/lactate_threshold_run.py
lactolyse/analyses/utils.py
lactolyse/executors/__init__.py
lactolyse/executors/docker.py
lactolyse/executors/local.py
lactolyse/management/__init__.py
lactolyse/management/commands/__init__.py
lactolyse/management/commands/listdockerimages.py
lactolyse/migrations/0001_initial.py
lactolyse/migrations/0002_add_results.py
lactolyse/migrations/0003_add_contributor.py
lactolyse/migrations/0004_conconi_test.py
lactolyse/migrations/0005_conconi_report_location.py
lactolyse/migrations/0006_lactate_run_analysis.py
lactolyse/migrations/0007_critical_power.py
lactolyse/migrations/__init__.py
lactolyse/static/lactolyse/css/custom.css
lactolyse/templates/__base__.html
lactolyse/templates/__footer__.html
lactolyse/templates/__header__.html
lactolyse/templates/__menu__.html
lactolyse/templates/lactolyse/analyses_success.html
lactolyse/templates/lactolyse/conconi_test.html
lactolyse/templates/lactolyse/critical_power.html
lactolyse/templates/lactolyse/lactate_threshold.html
lactolyse/templates/lactolyse/lactate_threshold_run.html
lactolyse/templates/lactolyse/login.html
lactolyse/templates/lactolyse/select_analyses.html
lactolyse/templates/lactolyse/latex/conconi_test.tex
lactolyse/templates/lactolyse/latex/critical_power.tex
lactolyse/templates/lactolyse/latex/lactate_treshold.tex
lactolyse/templates/lactolyse/latex/lactate_treshold_run.tex
lactolyse/views/__init__.py
lactolyse/views/base.py
lactolyse/views/conconi_test.py
lactolyse/views/critical_power.py
lactolyse/views/download.py
lactolyse/views/lactate_threshold.py
lactolyse-0.9.0a15.dist-info/LICENSE
lactolyse-0.9.0a15.dist-info/METADATA
lactolyse-0.9.0a15.dist-info/WHEEL
lactolyse-0.9.0a15.dist-info/top_level.txt
lactolyse-0.9.0a15.dist-info/RECORD
